macids/__init__.py
macids/__main__.py
macids/netmon/__init__.py
macids/netmon/__main__.py
macids/netmon/download_geoip_db.py
macids/netmon/network_analyzer_tkinter.py
macids/netmon/network_monitor.py
macids-1.2.dist-info/LICENSE
macids-1.2.dist-info/METADATA
macids-1.2.dist-info/WHEEL
macids-1.2.dist-info/entry_points.txt
macids-1.2.dist-info/top_level.txt
macids-1.2.dist-info/RECORD
