Metadata-Version: 2.1
Name: MacIDS
Version: 1.2
Summary: macOS-based Intrusion Detection System using machine learning for adaptive network security
Home-page: https://github.com/Nandhan-KA/MacIDS
Author: Nandhan K
Author-email: developer.nandhank@gmail.com
Classifier: Programming Language :: Python :: 3
Classifier: License :: OSI Approved :: MIT License
Classifier: Operating System :: MacOS :: MacOS X
Classifier: Topic :: Security
Classifier: Topic :: System :: Networking :: Monitoring
Classifier: Topic :: Scientific/Engineering :: Artificial Intelligence
Requires-Python: >=3.7
License-File: LICENSE
Requires-Dist: tensorflow >=2.0.0
Requires-Dist: numpy >=1.18.0
Requires-Dist: pandas >=1.0.0
Requires-Dist: matplotlib >=3.1.0
Requires-Dist: scikit-learn >=0.22.0
Requires-Dist: pillow >=7.0.0
Requires-Dist: scapy >=2.5.0
Requires-Dist: psutil >=5.9.0
Requires-Dist: dnspython >=2.2.0
Requires-Dist: requests >=2.27.0
Requires-Dist: geoip2 >=4.6.0
